[
    {
        "name": "David Johnson",
        "age": "19",
        "phone_number": "9148803039"
    },
    {
        "name": "David Johnson",
        "age": "19",
        "phone_number": "9148803039"
    },
    {
        "name": "David Johnson",
        "age": "19",
        "phone_number": "9148803039"
    },
    {
        "name": "aadhinath",
        "age": "58",
        "phone_number": "12345567"
    },
    {
        "name": "Ayaan",
        "age": "19",
        "phone_number": "12345567"
    },
    {
        "name": "raheesh",
        "age": "19",
        "phone_number": "9019307090"
    },
    {
        "name": "azzem",
        "age": "19",
        "phone_number": "9019307090"
    },
    {
        "name": "sourabh",
        "age": "19",
        "phone_number": "12345567"
    },
    {
        "name": "sankeerth",
        "age": "19",
        "phone_number": "12345567"
    },
    {
        "name": "arshin",
        "age": "19",
        "phone_number": "12345567"
    },
    {
        "name": "salman khan",
        "age": "92",
        "phone_number": "69669420"
    },
    {
        "name": "naruto",
        "age": "20",
        "phone_number": "69669420"
    }
]